{"id":"318734383_An_Axiomatic_Basis_for_Computer_Programming","abstract":"In this paper an attempt is made to explore the logical foundations of computer programming by use of techniques which were first applied in the study of geometry and have later been extended to other branches of mathematics. This involves the elucidation of sets of axioms and rules of inference which can be used in proofs of the properties of computer programs. Examples are given of such axioms and rules, and a formal proof of a simple theorem is displayed. Finally, it is argued that important advantages, both theoretical and practical, may follow from a pursuance of these topics. © 1983, ACM. All rights reserved.","authors":["C.A.R. Hoare"],"meta":["January 1983","DOI:10.1145/357980.358001"],"references":["251379520_Numerical_Analysis_as_an_independent_science","242502673_Assigning_Meanings_to_Programs","226632430_Proof_of_Algorithms_by_General_Snapshots"]}