{"id":"337944176_Entrevista_com_Marlos_Cholodovskis_Machado","abstract":"O entrevistado dessa edição da revista Conexão Ciência é o Dr. Marlos Cholodovskis Machado, bacharel e mestre em ciência da computação pela Universidade Federal de Minas Gerais, e doutor em ciência da computação pela University of Alberta, Canadá. Marlos tem recebido diversos reconhecimentos ao longo de sua carreira, incluindo prêmios como melhor aluno da sua graduaçāo, melhor trabalho em andamento do seu mestrado e, atualmente, é um dos indicados para o prêmio de melhor tese doutorado do departamento de ciência da computaçāo da University of Alberta. Ele publica com frequência nas principais conferências e periódicos da área e durante seu doutorado fez\nestágios na Microsoft Research, IBM Research, e DeepMind. É pesquisador no Google Brain, em Montréal. Os seus interesses de pesquisa residem, de forma geral, em inteligência artificial, mais especificamente em aprendizado de máquina e aprendizado por reforço.","authors":["Heslley Machado Silva"],"meta":["December 2019Conexão Ciência 14(4):1-3","DOI:10.24862/cco.v14i4.1199"],"references":[]}