{"id":"340595572_Las_Ciencias_de_la_Computacion_en_el_Curriculum_Escolar","abstract":"En la última década la enseñanza de los conceptos sobre Ciencias de la Computación irrumpe con fuerza en las instituciones escolares, contando con gran consenso y siendo reconocida como disciplina prioritaria, tanto en países desarrollados como en desarrollo.\n\nArgentina se encuentra articulando diversas acciones que proponen la implementación de estrategias para aproximar las Ciencias de la Computación a la Escuela Secundaria.\n\nEn este contexto en 2018 la provincia de Neuquén incorpora la asignatura Informática al Ciclo Básico Común para la educación secundaria con un fuerte anclaje a las Ciencias de la Computación.\n\nSin embargo, en el mapa curricular nacional las Ciencias de la Computación tienen una distribución desigual subsumida, generalmente, en el área de Tecnología.\n\nSe propone analizar cuáles son los Paradigmas y Enfoques con que la computación se representa en los documentos curriculares.\n\nLa línea de investigación busca identificar paradigmas y enfoques que logren constituirse en categorías de análisis satisfactorias para explicar la situación de la computación en los diseños curriculares.\n\nLa relevancia de este estudio radica en la necesidad de disponer de herramientas que permitan mejorar la comprensión del sentido pedagógico con el que la computación se expresa en las propuestas de enseñanza oficiales para el nivel secundario.","authors":["Gisela Branchini","Marcos Manuel Cortez","Jorge Rodriguez"],"meta":["April 2019","Project: AGENTES INTELIGENTES. MODELOS FORMALES Y APLICACIONES PARA LA EDUCACIÓN."],"references":["301716623_Computer_science_in_K-12_school_curricula_of_the_2lst_century_Why_what_and_when","254310228_Teachers_Public_Life_and_Curriculum_Reform"]}