{"id":"343685518_Generalization_and_Optimization_of_Some_Algorithms","abstract":"This article presents techniques for generalization and optimization of some algorithms in number theory and one in analytical geometry, which finding practical application in other problems. All algorithms have a software implementation in Microsoft Visual Studio 6.0 SP 6 as console C++ applications.","authors":["Anton Iliev","Nikola Valchanov","Todorka Terzieva"],"meta":["May 2009","Conference: Plovdiv, ADIS, May 12-13, Collection of scientific works of National Conference \"Education in Information Society\", 52-58"],"references":[]}