{"id":"350817873_Biden_pursues_giant_boost_for_science_spending","abstract":"US president’s first budget proposal emphasizes applied research and public health, and aims to tackle climate change and racial injustice. US president’s first budget proposal emphasizes applied research and public health, and aims to tackle climate change and racial injustice.","authors":["Jeff Tollefson","Amy Maxmen","Ariana Remmel","Nidhi Subbaraman"],"meta":["April 2021Nature 592(7855)","DOI:10.1038/d41586-021-00897-0"],"references":[]}