{"id":"40967140_La_Disponibilidad_estrategica_de_los_activos_intangibles","abstract":"Para muchas empresas, las capacidades de los empleados, los sistemas de tecnología de la información y la cultura organizativa son mucho más valiosos que sus activos tangibles. A diferencia de los activos financieros y materiales, a los competidores les resulta muy difícil imitar los activos intangibles, lo cual convierte a estos en una fuente de ventaja competitiva sostenible","authors":["Robert S. Kaplan","David P. Norton"],"meta":["January 2004"],"references":[]}